{"nodes": [{"id": "chapter_04", "label": "The Secret Performance", "file_type": "document", "source_file": "wiki/chapters/04-the-secret-performance.md", "source_location": null, "source_url": null, "captured_at": null, "author": null, "contributor": null}, {"id": "concept_witness-generation", "label": "Witness Generation", "file_type": "document", "source_file": "wiki/chapters/04-the-secret-performance.md", "source_location": null, "source_url": null, "captured_at": null, "author": null, "contributor": null}, {"id": "concept_poseidon", "label": "Poseidon Hash", "file_type": "document", "source_file": "wiki/chapters/04-the-secret-performance.md", "source_location": null, "source_url": null, "captured_at": null, "author": null, "contributor": null}, {"id": "concept_reinforced-concrete", "label": "Reinforced Concrete Hash", "file_type": "document", "source_file": "wiki/chapters/04-the-secret-performance.md", "source_location": null, "source_url": null, "captured_at": null, "author": null, "contributor": null}, {"id": "concept_jolt", "label": "Jolt zkVM", "file_type": "document", "source_file": "wiki/chapters/04-the-secret-performance.md", "source_location": null, "source_url": null, "captured_at": null, "author": null, "contributor": null}], "edges": [{"source": "chapter_04", "target": "concept_witness-generation", "relation": "references", "confidence": "EXTRACTED", "source_file": "wiki/chapters/04-the-secret-performance.md", "source_location": null, "weight": 1.0}, {"source": "chapter_04", "target": "concept_poseidon", "relation": "references", "confidence": "EXTRACTED", "source_file": "wiki/chapters/04-the-secret-performance.md", "source_location": null, "weight": 1.0}, {"source": "chapter_04", "target": "concept_reinforced-concrete", "relation": "references", "confidence": "EXTRACTED", "source_file": "wiki/chapters/04-the-secret-performance.md", "source_location": null, "weight": 1.0}, {"source": "chapter_04", "target": "concept_midnight", "relation": "references", "confidence": "EXTRACTED", "source_file": "wiki/chapters/04-the-secret-performance.md", "source_location": null, "weight": 1.0}, {"source": "chapter_04", "target": "concept_jolt", "relation": "references", "confidence": "EXTRACTED", "source_file": "wiki/chapters/04-the-secret-performance.md", "source_location": null, "weight": 1.0}], "hyperedges": []}