{"nodes": [{"id": "ref-29_gentry-fhe", "label": "Fully Homomorphic Encryption Using Ideal Lattices", "file_type": "paper", "source_file": "references/ch09/ref-29-gentry-fhe.pdf", "source_location": null, "source_url": null, "captured_at": null, "author": null, "contributor": null}, {"id": "concept_bootstrapping", "label": "Bootstrapping (FHE)", "file_type": "paper", "source_file": "references/ch09/ref-29-gentry-fhe.pdf", "source_location": "p.1 (abstract)", "source_url": null, "captured_at": null, "author": null, "contributor": null}, {"id": "person_craig-gentry", "label": "Craig Gentry", "file_type": "paper", "source_file": "references/ch09/ref-29-gentry-fhe.pdf", "source_location": "p.1 (title page)", "source_url": null, "captured_at": null, "author": null, "contributor": null}], "edges": [{"source": "ref-29_gentry-fhe", "target": "concept_fhe", "relation": "defines", "confidence": "EXTRACTED", "source_file": "references/ch09/ref-29-gentry-fhe.pdf", "source_location": "p.1 (abstract)", "weight": 1.0}, {"source": "ref-29_gentry-fhe", "target": "concept_bootstrapping", "relation": "defines", "confidence": "EXTRACTED", "source_file": "references/ch09/ref-29-gentry-fhe.pdf", "source_location": "p.1 (abstract)", "weight": 1.0}, {"source": "ref-29_gentry-fhe", "target": "concept_lattice", "relation": "conceptually_related_to", "confidence": "EXTRACTED", "source_file": "references/ch09/ref-29-gentry-fhe.pdf", "source_location": "p.1 (abstract, ideal lattices)", "weight": 1.0}, {"source": "ref-29_gentry-fhe", "target": "person_craig-gentry", "relation": "conceptually_related_to", "confidence": "EXTRACTED", "source_file": "references/ch09/ref-29-gentry-fhe.pdf", "source_location": "p.1 (title page, author)", "weight": 1.0}], "hyperedges": []}